{
    "_description": "Experiment Metadata Checklist Focused on chromosome conformation capture",
    "checklist_group": "BEYOND_DNA",
    "checklist_id": "EXC000040",
    "checklist_name": "CHROMOSOME CONFORMATION CAPTURE specific",
    "checklist_version": "v1",
    "experiment_attribute": {
        "_insert_field_a": "",
        "_insert_field_b": "",
        "_insert_field_c": "",
        "experiment_context_type": "baseline",
        "key_experimental_factors": []
    },
    "experiment_name": "",
    "experiment_type": "CHROMOSOME_CONFORMATION_CAPTURE",
    "experiment_type_definition": "",
    "experiment_type_ontology_id": "EDAM:",
    "insert_size": 0,
    "instrument_model": "",
    "instrument_platform": "",
    "library_description": "",
    "library_layout": "",
    "library_name": "",
    "library_selection": "",
    "library_source": "GENOMIC???",
    "library_strategy": "",
    "sample_accession": "",
    "sequencing_protocol": "",
    "study_id": ""
}